miniad/__init__.py
miniad/functional.py
miniad/tensor.py
miniad/utils.py
miniad-0.1.1.dist-info/LICENSE
miniad-0.1.1.dist-info/METADATA
miniad-0.1.1.dist-info/WHEEL
miniad-0.1.1.dist-info/top_level.txt
miniad-0.1.1.dist-info/RECORD
