Metadata-Version: 2.1
Name: miniad
Version: 0.1.1
Summary: Another mini autograd engine with a PyTorch-like API.
Home-page: https://github.com/basicv8vc/miniautodiff
Author: basicv8vc
Author-email: basicv8vc@gmail.com
License: UNKNOWN
Platform: UNKNOWN
Classifier: Programming Language :: Python :: 3
Classifier: License :: OSI Approved :: MIT License
Classifier: Operating System :: OS Independent
Requires-Python: >=3.6
